chinu9653s_tool/__init__.py
chinu9653s_tool/tools.py
chinu9653s_tool/decorator/__init__.py
chinu9653s_tool/decorator/warning/__init__.py
chinu9653s_tool/decorator/warning/not_used_return_value.py
chinu9653s_tool-0.0.5.dist-info/METADATA
chinu9653s_tool-0.0.5.dist-info/WHEEL
chinu9653s_tool-0.0.5.dist-info/top_level.txt
chinu9653s_tool-0.0.5.dist-info/RECORD
