Metadata-Version: 2.1
Name: chinu9653s-tool
Version: 0.0.5
Summary: This is a sample Python package.
Author-email: Chinu9653 <juyoung9653@gamil.com>
License: MIT
Project-URL: Homepage, https://github.com/juyoung9653/chinu9653s_tool
Keywords: sample,tool
Classifier: Programming Language :: Python :: 3
Classifier: License :: OSI Approved :: MIT License
Requires-Python: >=3.6
Requires-Dist: json5
